flask_logging/__init__.py
flask_logging/config.py
flask_logging/core.py
flask_logging/defaults.cfg
flask_logging/docker.py
flask_logging/filters.py
flask_logging/flask.py
flask_logging/handlers/__init__.py
flask_logging/handlers/click.py
flask_logging/handlers/common.py
flask_logging/handlers/json.py
flask_logging/handlers/redis.py
flask_logging/loglevel.py
flask_logging/progress.py
flask_logging/py.typed
flask_logging/request_context.py
flask_logging_helpers-0.4.2.dist-info/WHEEL
flask_logging_helpers-0.4.2.dist-info/METADATA
flask_logging_helpers-0.4.2.dist-info/RECORD
