Metadata-Version: 2.1
Name: flask-logging-helpers
Version: 0.4.2
Summary: Logging tools for flask
License: MIT
Author: Alex Rudy
Author-email: opensource@alexrudy.net
Requires-Python: >=3.7,<4.0
Classifier: License :: OSI Approved :: MIT License
Classifier: Programming Language :: Python :: 3
Classifier: Programming Language :: Python :: 3.7
Classifier: Programming Language :: Python :: 3.8
Classifier: Programming Language :: Python :: 3.9
Provides-Extra: docker
Provides-Extra: redis
Requires-Dist: blinker (>=1.4,<2.0)
Requires-Dist: docker (>=4.4.4,<5.0.0); extra == "docker"
Requires-Dist: flask (>=1.1.2,<2.0.0)
Requires-Dist: pyyaml (>=5.3.1,<6.0.0)
Requires-Dist: redis (>=3.5.3,<4.0.0); extra == "redis"
